nr/__init__.py
nr/utils/__init__.py
nr/utils/git/__init__.py
nr/utils/git/py.typed
nr.utils.git-0.4.1.dist-info/LICENSE.txt
nr.utils.git-0.4.1.dist-info/METADATA
nr.utils.git-0.4.1.dist-info/WHEEL
nr.utils.git-0.4.1.dist-info/top_level.txt
nr.utils.git-0.4.1.dist-info/RECORD
