Metadata-Version: 2.1
Name: nr.utils.git
Version: 0.4.1
Summary: A simple wrapper around the Git CLI.
Home-page: https://git.niklasrosenstein.com/NiklasRosenstein/nr
Author: Niklas Rosenstein
Author-email: rosensteinniklas@gmail.com
License: MIT
Platform: UNKNOWN
Requires-Python: >=3.4.0,<4.0.0
License-File: LICENSE.txt
Requires-Dist: deprecated (<2.0.0,>=1.2.0)
